{"name":"Татьяна Доронина “Дневник актрисы”","bookImage":"https://storage.googleapis.com/audiobook_knigi/AudioBooks/536/bookImage.png","author":"Татьяна Доронина","genre":"биографии","reader":"Екатерина Хлыстова","rating":0.0,"bookDescription":"Аудиокнига “Дневник актрисы” автора Татьяны Дорониной . Книга Татьяны Дорониной написана удивительно тонко и в то же время ярко и выразительно. И интересна не только тем, что на ее страницах мы встречаемся с Георгием Товстоноговым и Иннокентием Смоктуновским, слушать аудиокнигу онлайн »","bookUrlID":"10000536","playlist":[{"comment":"Дневник актрисы. Глава 1 из 15 download","file":"https://archive.org/download/15..1515_201709/01.%20%D0%94%D0%BD%D0%B5%D0%B2%D0%BD%D0%B8%D0%BA%20%D0%B0%D0%BA%D1%82%D1%80%D0%B8%D1%81%D1%8B.%20%D0%93%D0%BB%D0%B0%D0%B2%D0%B0%201%20%D0%B8%D0%B7%2015.mp3"},{"comment":"Дневник актрисы. Глава 2 из 15 download","file":"https://archive.org/download/15..1515_201709/02.%20%D0%94%D0%BD%D0%B5%D0%B2%D0%BD%D0%B8%D0%BA%20%D0%B0%D0%BA%D1%82%D1%80%D0%B8%D1%81%D1%8B.%20%D0%93%D0%BB%D0%B0%D0%B2%D0%B0%202%20%D0%B8%D0%B7%2015.mp3"},{"comment":"Дневник актрисы. Глава 3 из 15 download","file":"https://archive.org/download/15..1515_201709/03.%20%D0%94%D0%BD%D0%B5%D0%B2%D0%BD%D0%B8%D0%BA%20%D0%B0%D0%BA%D1%82%D1%80%D0%B8%D1%81%D1%8B.%20%D0%93%D0%BB%D0%B0%D0%B2%D0%B0%203%20%D0%B8%D0%B7%2015.mp3"},{"comment":"Дневник актрисы. Глава 4 из 15 download","file":"https://archive.org/download/15..1515_201709/04.%20%D0%94%D0%BD%D0%B5%D0%B2%D0%BD%D0%B8%D0%BA%20%D0%B0%D0%BA%D1%82%D1%80%D0%B8%D1%81%D1%8B.%20%D0%93%D0%BB%D0%B0%D0%B2%D0%B0%204%20%D0%B8%D0%B7%2015.mp3"},{"comment":"Дневник актрисы. Глава 5 из 15 download","file":"https://archive.org/download/15..1515_201709/05.%20%D0%94%D0%BD%D0%B5%D0%B2%D0%BD%D0%B8%D0%BA%20%D0%B0%D0%BA%D1%82%D1%80%D0%B8%D1%81%D1%8B.%20%D0%93%D0%BB%D0%B0%D0%B2%D0%B0%205%20%D0%B8%D0%B7%2015.mp3"},{"comment":"Дневник актрисы. Глава 6 из 15 download","file":"https://archive.org/download/15..1515_201709/06.%20%D0%94%D0%BD%D0%B5%D0%B2%D0%BD%D0%B8%D0%BA%20%D0%B0%D0%BA%D1%82%D1%80%D0%B8%D1%81%D1%8B.%20%D0%93%D0%BB%D0%B0%D0%B2%D0%B0%206%20%D0%B8%D0%B7%2015.mp3"},{"comment":"Дневник актрисы. Глава 7 из 15 download","file":"https://archive.org/download/15..1515_201709/07.%20%D0%94%D0%BD%D0%B5%D0%B2%D0%BD%D0%B8%D0%BA%20%D0%B0%D0%BA%D1%82%D1%80%D0%B8%D1%81%D1%8B.%20%D0%93%D0%BB%D0%B0%D0%B2%D0%B0%207%20%D0%B8%D0%B7%2015.mp3"},{"comment":"Дневник актрисы. Глава 8 из 15 download","file":"https://archive.org/download/15..1515_201709/08.%20%D0%94%D0%BD%D0%B5%D0%B2%D0%BD%D0%B8%D0%BA%20%D0%B0%D0%BA%D1%82%D1%80%D0%B8%D1%81%D1%8B.%20%D0%93%D0%BB%D0%B0%D0%B2%D0%B0%208%20%D0%B8%D0%B7%2015.mp3"},{"comment":"Дневник актрисы. Глава 9 из 15 download","file":"https://archive.org/download/15..1515_201709/09.%20%D0%94%D0%BD%D0%B5%D0%B2%D0%BD%D0%B8%D0%BA%20%D0%B0%D0%BA%D1%82%D1%80%D0%B8%D1%81%D1%8B.%20%D0%93%D0%BB%D0%B0%D0%B2%D0%B0%209%20%D0%B8%D0%B7%2015.mp3"},{"comment":"Дневник актрисы. Глава 10 из 15 download","file":"https://archive.org/download/15..1515_201709/10.%20%D0%94%D0%BD%D0%B5%D0%B2%D0%BD%D0%B8%D0%BA%20%D0%B0%D0%BA%D1%82%D1%80%D0%B8%D1%81%D1%8B.%20%D0%93%D0%BB%D0%B0%D0%B2%D0%B0%2010%20%D0%B8%D0%B7%2015.mp3"},{"comment":"Дневник актрисы. Глава 11 из 15 download","file":"https://archive.org/download/15..1515_201709/11.%20%D0%94%D0%BD%D0%B5%D0%B2%D0%BD%D0%B8%D0%BA%20%D0%B0%D0%BA%D1%82%D1%80%D0%B8%D1%81%D1%8B.%20%D0%93%D0%BB%D0%B0%D0%B2%D0%B0%2011%20%D0%B8%D0%B7%2015.mp3"},{"comment":"Дневник актрисы. Глава 12 из 15 download","file":"https://archive.org/download/15..1515_201709/12.%20%D0%94%D0%BD%D0%B5%D0%B2%D0%BD%D0%B8%D0%BA%20%D0%B0%D0%BA%D1%82%D1%80%D0%B8%D1%81%D1%8B.%20%D0%93%D0%BB%D0%B0%D0%B2%D0%B0%2012%20%D0%B8%D0%B7%2015.mp3"},{"comment":"Дневник актрисы. Глава 13 из 15 download","file":"https://archive.org/download/15..1515_201709/13.%20%D0%94%D0%BD%D0%B5%D0%B2%D0%BD%D0%B8%D0%BA%20%D0%B0%D0%BA%D1%82%D1%80%D0%B8%D1%81%D1%8B.%20%D0%93%D0%BB%D0%B0%D0%B2%D0%B0%2013%20%D0%B8%D0%B7%2015.mp3"},{"comment":"Дневник актрисы. Глава 14 из 15 download","file":"https://archive.org/download/15..1515_201709/14.%20%D0%94%D0%BD%D0%B5%D0%B2%D0%BD%D0%B8%D0%BA%20%D0%B0%D0%BA%D1%82%D1%80%D0%B8%D1%81%D1%8B.%20%D0%93%D0%BB%D0%B0%D0%B2%D0%B0%2014%20%D0%B8%D0%B7%2015.mp3"},{"comment":"Дневник актрисы. Глава 15 из 15 download","file":"https://archive.org/download/15..1515_201709/15.%20%D0%94%D0%BD%D0%B5%D0%B2%D0%BD%D0%B8%D0%BA%20%D0%B0%D0%BA%D1%82%D1%80%D0%B8%D1%81%D1%8B.%20%D0%93%D0%BB%D0%B0%D0%B2%D0%B0%2015%20%D0%B8%D0%B7%2015.mp3"}]}
