{"name":"А. Джерри Риддл “Ген Атлантиды”","bookImage":"https://storage.googleapis.com/audiobook_knigi/AudioBooks/4315/bookImage.png","author":"А.-Джерри Риддл","genre":"фантастика-онлайн","reader":"Сергей Кирсанов","rating":0.0,"bookDescription":"Аудиокнига “Ген Атлантиды” автора А. Джерри Риддл это первая книга из трилогии “Тайна происхождения”. Люди, называющие себя Иммари, живая память о тысячелетиях существования человечества. Нет племени древнее их. Все эти тысячелетия они хранили тайну происхождения своего рода, не открывая ее никому. И все это время искали следы своего древнего заклятого врага, слушать аудиокнигу онлайн »","bookUrlID":"10004315","playlist":[{"comment":"Пролог download","file":"https://archive.org/download/013.13_201712/000.%20%D0%9F%D1%80%D0%BE%D0%BB%D0%BE%D0%B3.mp3"},{"comment":"Часть первая. Джакарта в огне. Глава 1 download","file":"https://archive.org/download/013.13_201712/001.%20%D0%93%D0%BB%D0%B0%D0%B2%D0%B0%201.mp3"},{"comment":"Глава 2 download","file":"https://archive.org/download/013.13_201712/002.%20%D0%93%D0%BB%D0%B0%D0%B2%D0%B0%202.mp3"},{"comment":"Глава 3 download","file":"https://archive.org/download/013.13_201712/003.%20%D0%93%D0%BB%D0%B0%D0%B2%D0%B0%203.mp3"},{"comment":"Глава 4 download","file":"https://archive.org/download/013.13_201712/004.%20%D0%93%D0%BB%D0%B0%D0%B2%D0%B0%204.mp3"},{"comment":"Глава 5 download","file":"https://archive.org/download/013.13_201712/005.%20%D0%93%D0%BB%D0%B0%D0%B2%D0%B0%205.mp3"},{"comment":"Глава 6 download","file":"https://archive.org/download/013.13_201712/006.%20%D0%93%D0%BB%D0%B0%D0%B2%D0%B0%206.mp3"},{"comment":"Глава 7 download","file":"https://archive.org/download/013.13_201712/007.%20%D0%93%D0%BB%D0%B0%D0%B2%D0%B0%207.mp3"},{"comment":"Глава 8 download","file":"https://archive.org/download/013.13_201712/008.%20%D0%93%D0%BB%D0%B0%D0%B2%D0%B0%208.mp3"},{"comment":"Глава 9 download","file":"https://archive.org/download/013.13_201712/009.%20%D0%93%D0%BB%D0%B0%D0%B2%D0%B0%209.mp3"},{"comment":"Глава 10 download","file":"https://archive.org/download/013.13_201712/010.%20%D0%93%D0%BB%D0%B0%D0%B2%D0%B0%2010.mp3"},{"comment":"Глава 11 download","file":"https://archive.org/download/013.13_201712/011.%20%D0%93%D0%BB%D0%B0%D0%B2%D0%B0%2011.mp3"},{"comment":"Глава 12 download","file":"https://archive.org/download/013.13_201712/012.%20%D0%93%D0%BB%D0%B0%D0%B2%D0%B0%2012.mp3"},{"comment":"Глава 13 download","file":"https://archive.org/download/013.13_201712/013.%20%D0%93%D0%BB%D0%B0%D0%B2%D0%B0%2013.mp3"},{"comment":"Глава 14 download","file":"https://archive.org/download/013.13_201712/014.%20%D0%93%D0%BB%D0%B0%D0%B2%D0%B0%2014.mp3"},{"comment":"Глава 15 download","file":"https://archive.org/download/013.13_201712/015.%20%D0%93%D0%BB%D0%B0%D0%B2%D0%B0%2015.mp3"},{"comment":"Глава 16 download","file":"https://archive.org/download/013.13_201712/016.%20%D0%93%D0%BB%D0%B0%D0%B2%D0%B0%2016.mp3"},{"comment":"Глава 17 download","file":"https://archive.org/download/013.13_201712/017.%20%D0%93%D0%BB%D0%B0%D0%B2%D0%B0%2017.mp3"},{"comment":"Глава 18 download","file":"https://archive.org/download/013.13_201712/018.%20%D0%93%D0%BB%D0%B0%D0%B2%D0%B0%2018.mp3"},{"comment":"Глава 19 download","file":"https://archive.org/download/013.13_201712/019.%20%D0%93%D0%BB%D0%B0%D0%B2%D0%B0%2019.mp3"},{"comment":"Глава 20 download","file":"https://archive.org/download/013.13_201712/020.%20%D0%93%D0%BB%D0%B0%D0%B2%D0%B0%2020.mp3"},{"comment":"Глава 21 download","file":"https://archive.org/download/013.13_201712/021.%20%D0%93%D0%BB%D0%B0%D0%B2%D0%B0%2021.mp3"},{"comment":"Глава 22 download","file":"https://archive.org/download/013.13_201712/022.%20%D0%93%D0%BB%D0%B0%D0%B2%D0%B0%2022.mp3"},{"comment":"Глава 23 download","file":"https://archive.org/download/013.13_201712/023.%20%D0%93%D0%BB%D0%B0%D0%B2%D0%B0%2023.mp3"},{"comment":"Глава 24 download","file":"https://archive.org/download/013.13_201712/024.%20%D0%93%D0%BB%D0%B0%D0%B2%D0%B0%2024.mp3"},{"comment":"Глава 25 download","file":"https://archive.org/download/013.13_201712/025.%20%D0%93%D0%BB%D0%B0%D0%B2%D0%B0%2025.mp3"},{"comment":"Глава 26 download","file":"https://archive.org/download/013.13_201712/026.%20%D0%93%D0%BB%D0%B0%D0%B2%D0%B0%2026.mp3"},{"comment":"Глава 27 download","file":"https://archive.org/download/013.13_201712/027.%20%D0%93%D0%BB%D0%B0%D0%B2%D0%B0%2027.mp3"},{"comment":"Глава 28 download","file":"https://archive.org/download/013.13_201712/028.%20%D0%93%D0%BB%D0%B0%D0%B2%D0%B0%2028.mp3"},{"comment":"Глава 29 download","file":"https://archive.org/download/013.13_201712/029.%20%D0%93%D0%BB%D0%B0%D0%B2%D0%B0%2029.mp3"},{"comment":"Глава 30 download","file":"https://archive.org/download/013.13_201712/030.%20%D0%93%D0%BB%D0%B0%D0%B2%D0%B0%2030.mp3"},{"comment":"Глава 31 download","file":"https://archive.org/download/013.13_201712/031.%20%D0%93%D0%BB%D0%B0%D0%B2%D0%B0%2031.mp3"},{"comment":"Глава 32 download","file":"https://archive.org/download/013.13_201712/032.%20%D0%93%D0%BB%D0%B0%D0%B2%D0%B0%2032.mp3"},{"comment":"Глава 33 download","file":"https://archive.org/download/013.13_201712/033.%20%D0%93%D0%BB%D0%B0%D0%B2%D0%B0%2033.mp3"},{"comment":"Глава 34 download","file":"https://archive.org/download/013.13_201712/034.%20%D0%93%D0%BB%D0%B0%D0%B2%D0%B0%2034.mp3"},{"comment":"Глава 35 download","file":"https://archive.org/download/013.13_201712/035.%20%D0%93%D0%BB%D0%B0%D0%B2%D0%B0%2035.mp3"},{"comment":"Глава 36 download","file":"https://archive.org/download/013.13_201712/036.%20%D0%93%D0%BB%D0%B0%D0%B2%D0%B0%2036.mp3"},{"comment":"Глава 37 download","file":"https://archive.org/download/013.13_201712/037.%20%D0%93%D0%BB%D0%B0%D0%B2%D0%B0%2037.mp3"},{"comment":"Глава 38 download","file":"https://archive.org/download/013.13_201712/038.%20%D0%93%D0%BB%D0%B0%D0%B2%D0%B0%2038.mp3"},{"comment":"Глава 39 download","file":"https://archive.org/download/013.13_201712/039.%20%D0%93%D0%BB%D0%B0%D0%B2%D0%B0%2039.mp3"},{"comment":"Часть вторая. Тибетский гобелен. Глава 40 download","file":"https://archive.org/download/013.13_201712/040.%20%D0%93%D0%BB%D0%B0%D0%B2%D0%B0%2040.mp3"},{"comment":"Глава 41 download","file":"https://archive.org/download/013.13_201712/041.%20%D0%93%D0%BB%D0%B0%D0%B2%D0%B0%2041.mp3"},{"comment":"Глава 42 download","file":"https://archive.org/download/013.13_201712/042.%20%D0%93%D0%BB%D0%B0%D0%B2%D0%B0%2042.mp3"},{"comment":"Глава 43 download","file":"https://archive.org/download/013.13_201712/043.%20%D0%93%D0%BB%D0%B0%D0%B2%D0%B0%2043.mp3"},{"comment":"Глава 44 download","file":"https://archive.org/download/013.13_201712/044.%20%D0%93%D0%BB%D0%B0%D0%B2%D0%B0%2044.mp3"},{"comment":"Глава 45 download","file":"https://archive.org/download/013.13_201712/045.%20%D0%93%D0%BB%D0%B0%D0%B2%D0%B0%2045.mp3"},{"comment":"Глава 46 download","file":"https://archive.org/download/013.13_201712/046.%20%D0%93%D0%BB%D0%B0%D0%B2%D0%B0%2046.mp3"},{"comment":"Глава 47 download","file":"https://archive.org/download/013.13_201712/047.%20%D0%93%D0%BB%D0%B0%D0%B2%D0%B0%2047.mp3"},{"comment":"Глава 48 download","file":"https://archive.org/download/013.13_201712/048.%20%D0%93%D0%BB%D0%B0%D0%B2%D0%B0%2048.mp3"},{"comment":"Глава 49 download","file":"https://archive.org/download/013.13_201712/049.%20%D0%93%D0%BB%D0%B0%D0%B2%D0%B0%2049.mp3"},{"comment":"Глава 50 download","file":"https://archive.org/download/013.13_201712/050.%20%D0%93%D0%BB%D0%B0%D0%B2%D0%B0%2050.mp3"},{"comment":"Глава 51 download","file":"https://archive.org/download/013.13_201712/051.%20%D0%93%D0%BB%D0%B0%D0%B2%D0%B0%2051.mp3"},{"comment":"Глава 52 download","file":"https://archive.org/download/013.13_201712/052.%20%D0%93%D0%BB%D0%B0%D0%B2%D0%B0%2052.mp3"},{"comment":"Глава 53 download","file":"https://archive.org/download/013.13_201712/053.%20%D0%93%D0%BB%D0%B0%D0%B2%D0%B0%2053.mp3"},{"comment":"Глава 54 download","file":"https://archive.org/download/013.13_201712/054.%20%D0%93%D0%BB%D0%B0%D0%B2%D0%B0%2054.mp3"},{"comment":"Глава 55 download","file":"https://archive.org/download/013.13_201712/055.%20%D0%93%D0%BB%D0%B0%D0%B2%D0%B0%2055.mp3"},{"comment":"Глава 56 download","file":"https://archive.org/download/013.13_201712/056.%20%D0%93%D0%BB%D0%B0%D0%B2%D0%B0%2056.mp3"},{"comment":"Глава 57 download","file":"https://archive.org/download/013.13_201712/057.%20%D0%93%D0%BB%D0%B0%D0%B2%D0%B0%2057.mp3"},{"comment":"Глава 58 download","file":"https://archive.org/download/013.13_201712/058.%20%D0%93%D0%BB%D0%B0%D0%B2%D0%B0%2058.mp3"},{"comment":"Глава 59 download","file":"https://archive.org/download/013.13_201712/059.%20%D0%93%D0%BB%D0%B0%D0%B2%D0%B0%2059.mp3"},{"comment":"Глава 60 download","file":"https://archive.org/download/013.13_201712/060.%20%D0%93%D0%BB%D0%B0%D0%B2%D0%B0%2060.mp3"},{"comment":"Глава 61 download","file":"https://archive.org/download/013.13_201712/061.%20%D0%93%D0%BB%D0%B0%D0%B2%D0%B0%2061.mp3"},{"comment":"Глава 62 download","file":"https://archive.org/download/013.13_201712/062.%20%D0%93%D0%BB%D0%B0%D0%B2%D0%B0%2062.mp3"},{"comment":"Глава 63 download","file":"https://archive.org/download/013.13_201712/063.%20%D0%93%D0%BB%D0%B0%D0%B2%D0%B0%2063.mp3"},{"comment":"Глава 64 download","file":"https://archive.org/download/013.13_201712/064.%20%D0%93%D0%BB%D0%B0%D0%B2%D0%B0%2064.mp3"},{"comment":"Глава 65 download","file":"https://archive.org/download/013.13_201712/065.%20%D0%93%D0%BB%D0%B0%D0%B2%D0%B0%2065.mp3"},{"comment":"Глава 66 download","file":"https://archive.org/download/013.13_201712/066.%20%D0%93%D0%BB%D0%B0%D0%B2%D0%B0%2066.mp3"},{"comment":"Глава 67 download","file":"https://archive.org/download/013.13_201712/067.%20%D0%93%D0%BB%D0%B0%D0%B2%D0%B0%2067.mp3"},{"comment":"Глава 68 download","file":"https://archive.org/download/013.13_201712/068.%20%D0%93%D0%BB%D0%B0%D0%B2%D0%B0%2068.mp3"},{"comment":"Глава 69 download","file":"https://archive.org/download/013.13_201712/069.%20%D0%93%D0%BB%D0%B0%D0%B2%D0%B0%2069.mp3"},{"comment":"Глава 70 download","file":"https://archive.org/download/013.13_201712/070.%20%D0%93%D0%BB%D0%B0%D0%B2%D0%B0%2070.mp3"},{"comment":"Глава 71 download","file":"https://archive.org/download/013.13_201712/071.%20%D0%93%D0%BB%D0%B0%D0%B2%D0%B0%2071.mp3"},{"comment":"Глава 72 download","file":"https://archive.org/download/013.13_201712/072.%20%D0%93%D0%BB%D0%B0%D0%B2%D0%B0%2072.mp3"},{"comment":"Глава 73 download","file":"https://archive.org/download/013.13_201712/073.%20%D0%93%D0%BB%D0%B0%D0%B2%D0%B0%2073.mp3"},{"comment":"Глава 74 download","file":"https://archive.org/download/013.13_201712/074.%20%D0%93%D0%BB%D0%B0%D0%B2%D0%B0%2074.mp3"},{"comment":"Глава 75 download","file":"https://archive.org/download/013.13_201712/075.%20%D0%93%D0%BB%D0%B0%D0%B2%D0%B0%2075.mp3"},{"comment":"Глава 76 download","file":"https://archive.org/download/013.13_201712/076.%20%D0%93%D0%BB%D0%B0%D0%B2%D0%B0%2076.mp3"},{"comment":"Глава 77 download","file":"https://archive.org/download/013.13_201712/077.%20%D0%93%D0%BB%D0%B0%D0%B2%D0%B0%2077.mp3"},{"comment":"Глава 78 download","file":"https://archive.org/download/013.13_201712/078.%20%D0%93%D0%BB%D0%B0%D0%B2%D0%B0%2078.mp3"},{"comment":"Глава 79 download","file":"https://archive.org/download/013.13_201712/079.%20%D0%93%D0%BB%D0%B0%D0%B2%D0%B0%2079.mp3"},{"comment":"Глава 80 download","file":"https://archive.org/download/013.13_201712/080.%20%D0%93%D0%BB%D0%B0%D0%B2%D0%B0%2080.mp3"},{"comment":"Глава 81 download","file":"https://archive.org/download/013.13_201712/081.%20%D0%93%D0%BB%D0%B0%D0%B2%D0%B0%2081.mp3"},{"comment":"Глава 82 download","file":"https://archive.org/download/013.13_201712/082.%20%D0%93%D0%BB%D0%B0%D0%B2%D0%B0%2082.mp3"},{"comment":"Глава 83 download","file":"https://archive.org/download/013.13_201712/083.%20%D0%93%D0%BB%D0%B0%D0%B2%D0%B0%2083.mp3"},{"comment":"Глава 84 download","file":"https://archive.org/download/013.13_201712/084.%20%D0%93%D0%BB%D0%B0%D0%B2%D0%B0%2084.mp3"},{"comment":"Глава 85 download","file":"https://archive.org/download/013.13_201712/085.%20%D0%93%D0%BB%D0%B0%D0%B2%D0%B0%2085.mp3"},{"comment":"Глава 86 download","file":"https://archive.org/download/013.13_201712/086.%20%D0%93%D0%BB%D0%B0%D0%B2%D0%B0%2086.mp3"},{"comment":"Глава 87 download","file":"https://archive.org/download/013.13_201712/087.%20%D0%93%D0%BB%D0%B0%D0%B2%D0%B0%2087.mp3"},{"comment":"Глава 88 download","file":"https://archive.org/download/013.13_201712/088.%20%D0%93%D0%BB%D0%B0%D0%B2%D0%B0%2088.mp3"},{"comment":"Глава 89 download","file":"https://archive.org/download/013.13_201712/089.%20%D0%93%D0%BB%D0%B0%D0%B2%D0%B0%2089.mp3"},{"comment":"Глава 90 download","file":"https://archive.org/download/013.13_201712/090.%20%D0%93%D0%BB%D0%B0%D0%B2%D0%B0%2090.mp3"},{"comment":"Глава 91 download","file":"https://archive.org/download/013.13_201712/091.%20%D0%93%D0%BB%D0%B0%D0%B2%D0%B0%2091.mp3"},{"comment":"Глава 92 download","file":"https://archive.org/download/013.13_201712/092.%20%D0%93%D0%BB%D0%B0%D0%B2%D0%B0%2092.mp3"},{"comment":"Глава 93 download","file":"https://archive.org/download/013.13_201712/093.%20%D0%93%D0%BB%D0%B0%D0%B2%D0%B0%2093.mp3"},{"comment":"Глава 94 download","file":"https://archive.org/download/013.13_201712/094.%20%D0%93%D0%BB%D0%B0%D0%B2%D0%B0%2094.mp3"},{"comment":"Часть третья. В катакомбах Атлантиды. Глава 95 download","file":"https://archive.org/download/013.13_201712/095.%20%D0%93%D0%BB%D0%B0%D0%B2%D0%B0%2095.mp3"},{"comment":"Глава 96 download","file":"https://archive.org/download/013.13_201712/096.%20%D0%93%D0%BB%D0%B0%D0%B2%D0%B0%2096.mp3"},{"comment":"Глава 97 download","file":"https://archive.org/download/013.13_201712/097.%20%D0%93%D0%BB%D0%B0%D0%B2%D0%B0%2097.mp3"},{"comment":"Глава 98 download","file":"https://archive.org/download/013.13_201712/098.%20%D0%93%D0%BB%D0%B0%D0%B2%D0%B0%2098.mp3"},{"comment":"Глава 99 download","file":"https://archive.org/download/013.13_201712/099.%20%D0%93%D0%BB%D0%B0%D0%B2%D0%B0%2099.mp3"},{"comment":"Глава 100 download","file":"https://archive.org/download/013.13_201712/100.%20%D0%93%D0%BB%D0%B0%D0%B2%D0%B0%20100.mp3"},{"comment":"Глава 101 download","file":"https://archive.org/download/013.13_201712/101.%20%D0%93%D0%BB%D0%B0%D0%B2%D0%B0%20101.mp3"},{"comment":"Глава 102 download","file":"https://archive.org/download/013.13_201712/102.%20%D0%93%D0%BB%D0%B0%D0%B2%D0%B0%20102.mp3"},{"comment":"Глава 103 download","file":"https://archive.org/download/013.13_201712/103.%20%D0%93%D0%BB%D0%B0%D0%B2%D0%B0%20103.mp3"},{"comment":"Глава 104 download","file":"https://archive.org/download/013.13_201712/104.%20%D0%93%D0%BB%D0%B0%D0%B2%D0%B0%20104.mp3"},{"comment":"Глава 105 download","file":"https://archive.org/download/013.13_201712/105.%20%D0%93%D0%BB%D0%B0%D0%B2%D0%B0%20105.mp3"},{"comment":"Глава 106 download","file":"https://archive.org/download/013.13_201712/106.%20%D0%93%D0%BB%D0%B0%D0%B2%D0%B0%20106.mp3"},{"comment":"Глава 107 download","file":"https://archive.org/download/013.13_201712/107.%20%D0%93%D0%BB%D0%B0%D0%B2%D0%B0%20107.mp3"},{"comment":"Глава 108 download","file":"https://archive.org/download/013.13_201712/108.%20%D0%93%D0%BB%D0%B0%D0%B2%D0%B0%20108.mp3"},{"comment":"Глава 109 download","file":"https://archive.org/download/013.13_201712/109.%20%D0%93%D0%BB%D0%B0%D0%B2%D0%B0%20109.mp3"},{"comment":"Глава 110 download","file":"https://archive.org/download/013.13_201712/110.%20%D0%93%D0%BB%D0%B0%D0%B2%D0%B0%20110.mp3"},{"comment":"Глава 111 download","file":"https://archive.org/download/013.13_201712/111.%20%D0%93%D0%BB%D0%B0%D0%B2%D0%B0%20111.mp3"},{"comment":"Глава 112 download","file":"https://archive.org/download/013.13_201712/112.%20%D0%93%D0%BB%D0%B0%D0%B2%D0%B0%20112.mp3"},{"comment":"Глава 113 download","file":"https://archive.org/download/013.13_201712/113.%20%D0%93%D0%BB%D0%B0%D0%B2%D0%B0%20113.mp3"},{"comment":"Глава 114 download","file":"https://archive.org/download/013.13_201712/114.%20%D0%93%D0%BB%D0%B0%D0%B2%D0%B0%20114.mp3"},{"comment":"Глава 115 download","file":"https://archive.org/download/013.13_201712/115.%20%D0%93%D0%BB%D0%B0%D0%B2%D0%B0%20115.mp3"},{"comment":"Глава 116 download","file":"https://archive.org/download/013.13_201712/116.%20%D0%93%D0%BB%D0%B0%D0%B2%D0%B0%20116.mp3"},{"comment":"Глава 117 download","file":"https://archive.org/download/013.13_201712/117.%20%D0%93%D0%BB%D0%B0%D0%B2%D0%B0%20117.mp3"},{"comment":"Глава 118 download","file":"https://archive.org/download/013.13_201712/118.%20%D0%93%D0%BB%D0%B0%D0%B2%D0%B0%20118.mp3"},{"comment":"Глава 119 download","file":"https://archive.org/download/013.13_201712/119.%20%D0%93%D0%BB%D0%B0%D0%B2%D0%B0%20119.mp3"},{"comment":"Глава 120 download","file":"https://archive.org/download/013.13_201712/120.%20%D0%93%D0%BB%D0%B0%D0%B2%D0%B0%20120.mp3"},{"comment":"Глава 121 download","file":"https://archive.org/download/013.13_201712/121.%20%D0%93%D0%BB%D0%B0%D0%B2%D0%B0%20121.mp3"},{"comment":"Глава 122 download","file":"https://archive.org/download/013.13_201712/122.%20%D0%93%D0%BB%D0%B0%D0%B2%D0%B0%20122.mp3"},{"comment":"Глава 123 download","file":"https://archive.org/download/013.13_201712/123.%20%D0%93%D0%BB%D0%B0%D0%B2%D0%B0%20123.mp3"},{"comment":"Глава 124 download","file":"https://archive.org/download/013.13_201712/124.%20%D0%93%D0%BB%D0%B0%D0%B2%D0%B0%20124.mp3"},{"comment":"Глава 125 download","file":"https://archive.org/download/013.13_201712/125.%20%D0%93%D0%BB%D0%B0%D0%B2%D0%B0%20125.mp3"},{"comment":"Глава 126 download","file":"https://archive.org/download/013.13_201712/126.%20%D0%93%D0%BB%D0%B0%D0%B2%D0%B0%20126.mp3"},{"comment":"Глава 127 download","file":"https://archive.org/download/013.13_201712/127.%20%D0%93%D0%BB%D0%B0%D0%B2%D0%B0%20127.mp3"},{"comment":"Глава 128 download","file":"https://archive.org/download/013.13_201712/128.%20%D0%93%D0%BB%D0%B0%D0%B2%D0%B0%20128.mp3"},{"comment":"Глава 129 download","file":"https://archive.org/download/013.13_201712/129.%20%D0%93%D0%BB%D0%B0%D0%B2%D0%B0%20129.mp3"},{"comment":"Глава 130 download","file":"https://archive.org/download/013.13_201712/130.%20%D0%93%D0%BB%D0%B0%D0%B2%D0%B0%20130.mp3"},{"comment":"Глава 131 download","file":"https://archive.org/download/013.13_201712/131.%20%D0%93%D0%BB%D0%B0%D0%B2%D0%B0%20131.mp3"},{"comment":"Глава 132 download","file":"https://archive.org/download/013.13_201712/132.%20%D0%93%D0%BB%D0%B0%D0%B2%D0%B0%20132.mp3"},{"comment":"Глава 133 download","file":"https://archive.org/download/013.13_201712/133.%20%D0%93%D0%BB%D0%B0%D0%B2%D0%B0%20133.mp3"},{"comment":"Глава 134 download","file":"https://archive.org/download/013.13_201712/134.%20%D0%93%D0%BB%D0%B0%D0%B2%D0%B0%20134.mp3"},{"comment":"Глава 135 download","file":"https://archive.org/download/013.13_201712/135.%20%D0%93%D0%BB%D0%B0%D0%B2%D0%B0%20135.mp3"},{"comment":"Глава 136 download","file":"https://archive.org/download/013.13_201712/136.%20%D0%93%D0%BB%D0%B0%D0%B2%D0%B0%20136.mp3"},{"comment":"Глава 137 download","file":"https://archive.org/download/013.13_201712/137.%20%D0%93%D0%BB%D0%B0%D0%B2%D0%B0%20137.mp3"},{"comment":"Глава 138 download","file":"https://archive.org/download/013.13_201712/138.%20%D0%93%D0%BB%D0%B0%D0%B2%D0%B0%20138.mp3"},{"comment":"Глава 139 download","file":"https://archive.org/download/013.13_201712/139.%20%D0%93%D0%BB%D0%B0%D0%B2%D0%B0%20139.mp3"},{"comment":"Глава 140 download","file":"https://archive.org/download/013.13_201712/140.%20%D0%93%D0%BB%D0%B0%D0%B2%D0%B0%20140.mp3"},{"comment":"Глава 141 download","file":"https://archive.org/download/013.13_201712/141.%20%D0%93%D0%BB%D0%B0%D0%B2%D0%B0%20141.mp3"},{"comment":"Глава 142 download","file":"https://archive.org/download/013.13_201712/142.%20%D0%93%D0%BB%D0%B0%D0%B2%D0%B0%20142.mp3"},{"comment":"Глава 143 download","file":"https://archive.org/download/013.13_201712/143.%20%D0%93%D0%BB%D0%B0%D0%B2%D0%B0%20143.mp3"},{"comment":"Глава 144 download","file":"https://archive.org/download/013.13_201712/144.%20%D0%93%D0%BB%D0%B0%D0%B2%D0%B0%20144.mp3"},{"comment":"Эпилог download","file":"https://archive.org/download/013.13_201712/145.%20%D0%AD%D0%BF%D0%B8%D0%BB%D0%BE%D0%B3.mp3"},{"comment":"Послесловие автора download","file":"https://archive.org/download/013.13_201712/146.%20%D0%9F%D0%BE%D1%81%D0%BB%D0%B5%D1%81%D0%BB%D0%BE%D0%B2%D0%B8%D0%B5%20%D0%B0%D0%B2%D1%82%D0%BE%D1%80%D0%B0.mp3"}]}
