{"name":"Анатолий Половинкин “Опасный груз или А-44”","bookImage":"https://storage.googleapis.com/audiobook_knigi/AudioBooks/4711/bookImage.png","author":"Анатолий Половинкин","genre":"фантастика-онлайн","reader":"Олег Шубин","rating":0.0,"bookDescription":"Аудиокнига “Опасный груз или А-44” автора Анатолия Половинкина. В двадцать втором веке холодные войны на Земле переросли в войны бактериологические. Правительство США посылает в звездную систему Альтаира космическую экспедицию, где на одной из планет был обнаружен смертельный вирус, слушать аудиокнигу онлайн »","bookUrlID":"10004711","playlist":[{"comment":"01.Опасный груз или А-44 download","file":"https://archive.org/download/a44_026_201602/a44_001.mp3"},{"comment":"02.Опасный груз или А-44 download","file":"https://archive.org/download/a44_026_201602/a44_002.mp3"},{"comment":"03.Опасный груз или А-44 download","file":"https://archive.org/download/a44_026_201602/a44_003.mp3"},{"comment":"04.Опасный груз или А-44 download","file":"https://archive.org/download/a44_026_201602/a44_004.mp3"},{"comment":"05.Опасный груз или А-44 download","file":"https://archive.org/download/a44_026_201602/a44_005.mp3"},{"comment":"06.Опасный груз или А-44 download","file":"https://archive.org/download/a44_026_201602/a44_006.mp3"},{"comment":"07.Опасный груз или А-44 download","file":"https://archive.org/download/a44_026_201602/a44_007.mp3"},{"comment":"08.Опасный груз или А-44 download","file":"https://archive.org/download/a44_026_201602/a44_008.mp3"},{"comment":"09.Опасный груз или А-44 download","file":"https://archive.org/download/a44_026_201602/a44_009.mp3"},{"comment":"10.Опасный груз или А-44 download","file":"https://archive.org/download/a44_026_201602/a44_010.mp3"},{"comment":"11.Опасный груз или А-44 download","file":"https://archive.org/download/a44_026_201602/a44_011.mp3"},{"comment":"12.Опасный груз или А-44 download","file":"https://archive.org/download/a44_026_201602/a44_012.mp3"},{"comment":"13.Опасный груз или А-44 download","file":"https://archive.org/download/a44_026_201602/a44_013.mp3"},{"comment":"14.Опасный груз или А-44 download","file":"https://archive.org/download/a44_026_201602/a44_014.mp3"},{"comment":"15.Опасный груз или А-44 download","file":"https://archive.org/download/a44_026_201602/a44_015.mp3"},{"comment":"16.Опасный груз или А-44 download","file":"https://archive.org/download/a44_026_201602/a44_016.mp3"},{"comment":"17.Опасный груз или А-44 download","file":"https://archive.org/download/a44_026_201602/a44_017.mp3"},{"comment":"18.Опасный груз или А-44 download","file":"https://archive.org/download/a44_026_201602/a44_018.mp3"},{"comment":"19.Опасный груз или А-44 download","file":"https://archive.org/download/a44_026_201602/a44_019.mp3"},{"comment":"20.Опасный груз или А-44 download","file":"https://archive.org/download/a44_026_201602/a44_020.mp3"},{"comment":"21.Опасный груз или А-44 download","file":"https://archive.org/download/a44_026_201602/a44_021.mp3"},{"comment":"22.Опасный груз или А-44 download","file":"https://archive.org/download/a44_026_201602/a44_022.mp3"},{"comment":"23.Опасный груз или А-44 download","file":"https://archive.org/download/a44_026_201602/a44_023.mp3"},{"comment":"24.Опасный груз или А-44 download","file":"https://archive.org/download/a44_026_201602/a44_024.mp3"},{"comment":"25.Опасный груз или А-44 download","file":"https://archive.org/download/a44_026_201602/a44_025.mp3"},{"comment":"26.Опасный груз или А-44 download","file":"https://archive.org/download/a44_026_201602/a44_026.mp3"},{"comment":"27.Опасный груз или А-44 download","file":"https://archive.org/download/a44_026_201602/a44_027.mp3"},{"comment":"28.Опасный груз или А-44 download","file":"https://archive.org/download/a44_026_201602/a44_028.mp3"},{"comment":"29.Опасный груз или А-44 download","file":"https://archive.org/download/a44_026_201602/a44_029.mp3"},{"comment":"30.Опасный груз или А-44 download","file":"https://archive.org/download/a44_026_201602/a44_030.mp3"},{"comment":"31.Опасный груз или А-44 download","file":"https://archive.org/download/a44_026_201602/a44_031.mp3"},{"comment":"32.Опасный груз или А-44 download","file":"https://archive.org/download/a44_026_201602/a44_032.mp3"},{"comment":"33.Опасный груз или А-44 download","file":"https://archive.org/download/a44_026_201602/a44_033.mp3"},{"comment":"34.Опасный груз или А-44 download","file":"https://archive.org/download/a44_026_201602/a44_034.mp3"},{"comment":"35.Опасный груз или А-44 download","file":"https://archive.org/download/a44_026_201602/a44_035.mp3"},{"comment":"36.Опасный груз или А-44 download","file":"https://archive.org/download/a44_026_201602/a44_036.mp3"},{"comment":"37.Опасный груз или А-44 download","file":"https://archive.org/download/a44_026_201602/a44_037.mp3"},{"comment":"38.Опасный груз или А-44 download","file":"https://archive.org/download/a44_026_201602/a44_038.mp3"},{"comment":"39.Опасный груз или А-44 download","file":"https://archive.org/download/a44_026_201602/a44_039.mp3"},{"comment":"40.Опасный груз или А-44 download","file":"https://archive.org/download/a44_026_201602/a44_040.mp3"},{"comment":"41.Опасный груз или А-44 download","file":"https://archive.org/download/a44_026_201602/a44_041.mp3"},{"comment":"42.Опасный груз или А-44 download","file":"https://archive.org/download/a44_026_201602/a44_042.mp3"},{"comment":"43.Опасный груз или А-44 download","file":"https://archive.org/download/a44_026_201602/a44_043.mp3"},{"comment":"44.Опасный груз или А-44 download","file":"https://archive.org/download/a44_026_201602/a44_044.mp3"},{"comment":"45.Опасный груз или А-44 download","file":"https://archive.org/download/a44_026_201602/a44_045.mp3"},{"comment":"46.Опасный груз или А-44 download","file":"https://archive.org/download/a44_026_201602/a44_046.mp3"},{"comment":"47.Опасный груз или А-44 download","file":"https://archive.org/download/a44_026_201602/a44_047.mp3"},{"comment":"48.Опасный груз или А-44 download","file":"https://archive.org/download/a44_026_201602/a44_048.mp3"},{"comment":"49.Опасный груз или А-44 download","file":"https://archive.org/download/a44_026_201602/a44_049.mp3"},{"comment":"50.Опасный груз или А-44 download","file":"https://archive.org/download/a44_026_201602/a44_050.mp3"},{"comment":"51.Опасный груз или А-44 download","file":"https://archive.org/download/a44_026_201602/a44_051.mp3"},{"comment":"52.Опасный груз или А-44 download","file":"https://archive.org/download/a44_026_201602/a44_052.mp3"},{"comment":"53.Опасный груз или А-44 download","file":"https://archive.org/download/a44_026_201602/a44_053.mp3"},{"comment":"54.Опасный груз или А-44 download","file":"https://archive.org/download/a44_026_201602/a44_054.mp3"},{"comment":"55.Опасный груз или А-44 download","file":"https://archive.org/download/a44_026_201602/a44_055.mp3"},{"comment":"56.Опасный груз или А-44 download","file":"https://archive.org/download/a44_026_201602/a44_056.mp3"}]}
