{"name":"Леонид Сергеев “Альма”","bookImage":"https://storage.googleapis.com/audiobook_knigi/AudioBooks/3829/bookImage.png","author":"Леонид Сергеев","genre":"русская-литература-онлайн","reader":"Татевик Мнацаканян","rating":0.0,"bookDescription":"Аудиокнига “Альма” автора Леонида Сергеева. Повесть “Альма” написана на основе реальных событий. Спасенная писателем собака всегда оставалась его преданным, искренним другом. В 2010 году за повесть “Альма” Леонид Анатольевич Сергеев был удостоен Международной литературной премии им. слушать аудиокнигу онлайн »","bookUrlID":"10003829","playlist":[{"comment":"01_Однажды зимой download","file":"https://archive.org/download/23DruzyaISoperniki/01_Odnazhdy%20zimoy.mp3"},{"comment":"02_Улыбчивая птичница download","file":"https://archive.org/download/23DruzyaISoperniki/02_Ulybchivaya%20ptichnitsa.mp3"},{"comment":"03_Некоторые размышления о гражданах собачьего племени download","file":"https://archive.org/download/23DruzyaISoperniki/03_Nekotorye%20razmyshleniya%20o%20grazhdanah%20sobachego%20plemeni.mp3"},{"comment":"04_Птичница показывает своё истинное лицо download","file":"https://archive.org/download/23DruzyaISoperniki/04_Ptichnitsa%20pokazyvaet%20svoYo%20istinnoe%20litso.mp3"},{"comment":"05_Неожиданный звонок download","file":"https://archive.org/download/23DruzyaISoperniki/05_Neozhidannyy%20zvonok.mp3"},{"comment":"06_Страшное зрелище download","file":"https://archive.org/download/23DruzyaISoperniki/06_Strashnoe%20zrelische.mp3"},{"comment":"07_Размышления на дороге download","file":"https://archive.org/download/23DruzyaISoperniki/07_Razmyshleniya%20na%20doroge.mp3"},{"comment":"08_Доброе сердце и золотые руки download","file":"https://archive.org/download/23DruzyaISoperniki/08_Dobroe%20serdtse%20i%20zolotye%20ruki.mp3"},{"comment":"09_На даче download","file":"https://archive.org/download/23DruzyaISoperniki/09_Na%20dache.mp3"},{"comment":"10_Вова, Мишка, Гришка и другие download","file":"https://archive.org/download/23DruzyaISoperniki/10_Vova%2C%20Mishka%2C%20Grishka%20i%20drugie.mp3"},{"comment":"11_Знакомство Альмы с моим братом download","file":"https://archive.org/download/23DruzyaISoperniki/11_Znakomstvo%20Almy%20s%20moim%20bratom.mp3"},{"comment":"12_Рассказ ветеринара download","file":"https://archive.org/download/23DruzyaISoperniki/12_Rasskaz%20veterinara.mp3"},{"comment":"13_Новая встреча с Неждановым download","file":"https://archive.org/download/23DruzyaISoperniki/13_Novaya%20vstrecha%20s%20Nezhdanovym.mp3"},{"comment":"14_Наши игры download","file":"https://archive.org/download/23DruzyaISoperniki/14_Nashi%20igry.mp3"},{"comment":"15_Собачья школа download","file":"https://archive.org/download/23DruzyaISoperniki/15_Sobachya%20shkola.mp3"},{"comment":"16_Третий приезд в лечебницу download","file":"https://archive.org/download/23DruzyaISoperniki/16_Tretiy%20priezd%20v%20lechebnitsu.mp3"},{"comment":"17_Яркий представитель нашего посёлка download","file":"https://archive.org/download/23DruzyaISoperniki/17_Yarkiy%20predstavitel%20nashego%20posYolka.mp3"},{"comment":"18_Маленький отважный путешественник download","file":"https://archive.org/download/23DruzyaISoperniki/18_Malenkiy%20otvazhnyy%20puteshestvennik.mp3"},{"comment":"19_Кое-какие горькие мысли download","file":"https://archive.org/download/23DruzyaISoperniki/19_Koe-kakie%20gorkie%20mysli.mp3"},{"comment":"20_Чудеса в нашем поселке download","file":"https://archive.org/download/23DruzyaISoperniki/20_Chudesa%20v%20nashem%20poselke.mp3"},{"comment":"21_Прощай лето download","file":"https://archive.org/download/23DruzyaISoperniki/21_Proschay%20leto.mp3"},{"comment":"22_Наш двор download","file":"https://archive.org/download/23DruzyaISoperniki/22_Nash%20dvor.mp3"},{"comment":"23_Друзья и соперники download","file":"https://archive.org/download/23DruzyaISoperniki/23_Druzya%20i%20soperniki.mp3"},{"comment":"24_Брат Альмы download","file":"https://archive.org/download/23DruzyaISoperniki/24_Brat%20Almy.mp3"},{"comment":"25_У Альмы открываются новые таланты download","file":"https://archive.org/download/23DruzyaISoperniki/25_U%20Almy%20otkryvayutsya%20novye%20talanty.mp3"},{"comment":"26_Половодье download","file":"https://archive.org/download/23DruzyaISoperniki/26_Polovode.mp3"},{"comment":"27_У Рахманова download","file":"https://archive.org/download/23DruzyaISoperniki/27_U%20Rahmanova.mp3"},{"comment":"28_На рынке в Истре download","file":"https://archive.org/download/23DruzyaISoperniki/28_Na%20rynke%20v%20Istre.mp3"},{"comment":"29_Маркиза download","file":"https://archive.org/download/23DruzyaISoperniki/29_Markiza.mp3"},{"comment":"30_У Альмы появляется поклонник download","file":"https://archive.org/download/23DruzyaISoperniki/30_U%20Almy%20poyavlyaetsya%20poklonnik.mp3"},{"comment":"31_Авиакатастрофа download","file":"https://archive.org/download/23DruzyaISoperniki/31_Aviakatastrofa.mp3"},{"comment":"32_Альма участвует в конкурсе красоты download","file":"https://archive.org/download/23DruzyaISoperniki/32_Alma%20uchastvuet%20v%20konkurse%20krasoty.mp3"},{"comment":"33_Мы спасаем Вову и не только его download","file":"https://archive.org/download/23DruzyaISoperniki/33_My%20spasaem%20Vovu%20i%20ne%20tolko%20ego.mp3"},{"comment":"34_Театральная студия download","file":"https://archive.org/download/23DruzyaISoperniki/34_Teatralnaya%20studiya.mp3"},{"comment":"35_Спектакль для пап и мам download","file":"https://archive.org/download/23DruzyaISoperniki/35_Spektakl%20dlya%20pap%20i%20mam.mp3"},{"comment":"36_Пьеса для Альмы download","file":"https://archive.org/download/23DruzyaISoperniki/36_Pesa%20dlya%20Almy.mp3"},{"comment":"37_Последняя download","file":"https://archive.org/download/23DruzyaISoperniki/37_Poslednyaya.mp3"}]}
