{"name":"Станислав Родионов “Быть может”","bookImage":"https://storage.googleapis.com/audiobook_knigi/AudioBooks/989/bookImage.png","author":"Станислав Родионов","genre":"детектив-онлайн","reader":"Валерий Стельмащук","rating":0.0,"bookDescription":"Аудиокнига “Быть может” автора Станислава Родионова. Молодая замужняя женщина стала получать анонимные письма любовного содержания. По просьбе соседки старший следователь прокуратуры Рябинин взялся выяснить, кто же пишет эти письма. слушать аудиокнигу онлайн »","bookUrlID":"10000989","playlist":[{"comment":"001 Быть может.mp3 download","file":"https://archive.org/download/abook7_yandex_009_201709/001%20%D0%91%D1%8B%D1%82%D1%8C%20%D0%BC%D0%BE%D0%B6%D0%B5%D1%82.mp3"},{"comment":"002 Быть может.mp3 download","file":"https://archive.org/download/abook7_yandex_009_201709/002%20%D0%91%D1%8B%D1%82%D1%8C%20%D0%BC%D0%BE%D0%B6%D0%B5%D1%82.mp3"},{"comment":"003 Быть может.mp3 download","file":"https://archive.org/download/abook7_yandex_009_201709/003%20%D0%91%D1%8B%D1%82%D1%8C%20%D0%BC%D0%BE%D0%B6%D0%B5%D1%82.mp3"},{"comment":"004 Быть может.mp3 download","file":"https://archive.org/download/abook7_yandex_009_201709/004%20%D0%91%D1%8B%D1%82%D1%8C%20%D0%BC%D0%BE%D0%B6%D0%B5%D1%82.mp3"},{"comment":"005 Быть может.mp3 download","file":"https://archive.org/download/abook7_yandex_009_201709/005%20%D0%91%D1%8B%D1%82%D1%8C%20%D0%BC%D0%BE%D0%B6%D0%B5%D1%82.mp3"},{"comment":"006 Быть может.mp3 download","file":"https://archive.org/download/abook7_yandex_009_201709/006%20%D0%91%D1%8B%D1%82%D1%8C%20%D0%BC%D0%BE%D0%B6%D0%B5%D1%82.mp3"},{"comment":"007 Быть может.mp3 download","file":"https://archive.org/download/abook7_yandex_009_201709/007%20%D0%91%D1%8B%D1%82%D1%8C%20%D0%BC%D0%BE%D0%B6%D0%B5%D1%82.mp3"},{"comment":"008 Быть может.mp3 download","file":"https://archive.org/download/abook7_yandex_009_201709/008%20%D0%91%D1%8B%D1%82%D1%8C%20%D0%BC%D0%BE%D0%B6%D0%B5%D1%82.mp3"},{"comment":"009 Быть может.mp3 download","file":"https://archive.org/download/abook7_yandex_009_201709/009%20%D0%91%D1%8B%D1%82%D1%8C%20%D0%BC%D0%BE%D0%B6%D0%B5%D1%82.mp3"},{"comment":"010 Быть может.mp3 download","file":"https://archive.org/download/abook7_yandex_009_201709/010%20%D0%91%D1%8B%D1%82%D1%8C%20%D0%BC%D0%BE%D0%B6%D0%B5%D1%82.mp3"},{"comment":"011 Быть может.mp3 download","file":"https://archive.org/download/abook7_yandex_009_201709/011%20%D0%91%D1%8B%D1%82%D1%8C%20%D0%BC%D0%BE%D0%B6%D0%B5%D1%82.mp3"},{"comment":"012 Быть может.mp3 download","file":"https://archive.org/download/abook7_yandex_009_201709/012%20%D0%91%D1%8B%D1%82%D1%8C%20%D0%BC%D0%BE%D0%B6%D0%B5%D1%82.mp3"}]}
