{"name":"Дин Кунц “До рая подать рукой”","bookImage":"https://storage.googleapis.com/audiobook_knigi/AudioBooks/4223/bookImage.png","author":"Дин Кунц","genre":"триллер","reader":"Вячеслав Герасимов","rating":0.0,"bookDescription":"Аудиокнига “До рая подать рукой” автора Дина Кунца.","bookUrlID":"10004223","playlist":[{"comment":"Кунц Дин - До рая подать рукой download","file":"https://archive.org/download/059DoRajaPodatRuroy/001_Do%20raja%20podat%27%20ruroy.mp3"},{"comment":"Кунц Дин - До рая подать рукой download","file":"https://archive.org/download/059DoRajaPodatRuroy/002_Do%20raja%20podat%27%20ruroy.mp3"},{"comment":"Кунц Дин - До рая подать рукой download","file":"https://archive.org/download/059DoRajaPodatRuroy/003_Do%20raja%20podat%27%20ruroy.mp3"},{"comment":"Кунц Дин - До рая подать рукой download","file":"https://archive.org/download/059DoRajaPodatRuroy/004_Do%20raja%20podat%27%20ruroy.mp3"},{"comment":"Кунц Дин - До рая подать рукой download","file":"https://archive.org/download/059DoRajaPodatRuroy/005_Do%20raja%20podat%27%20ruroy.mp3"},{"comment":"Кунц Дин - До рая подать рукой download","file":"https://archive.org/download/059DoRajaPodatRuroy/006_Do%20raja%20podat%27%20ruroy.mp3"},{"comment":"Кунц Дин - До рая подать рукой download","file":"https://archive.org/download/059DoRajaPodatRuroy/007_Do%20raja%20podat%27%20ruroy.mp3"},{"comment":"Кунц Дин - До рая подать рукой download","file":"https://archive.org/download/059DoRajaPodatRuroy/008_Do%20raja%20podat%27%20ruroy.mp3"},{"comment":"Кунц Дин - До рая подать рукой download","file":"https://archive.org/download/059DoRajaPodatRuroy/009_Do%20raja%20podat%27%20ruroy.mp3"},{"comment":"Кунц Дин - До рая подать рукой download","file":"https://archive.org/download/059DoRajaPodatRuroy/010_Do%20raja%20podat%27%20ruroy.mp3"},{"comment":"Кунц Дин - До рая подать рукой download","file":"https://archive.org/download/059DoRajaPodatRuroy/011_Do%20raja%20podat%27%20ruroy.mp3"},{"comment":"Кунц Дин - До рая подать рукой download","file":"https://archive.org/download/059DoRajaPodatRuroy/012_Do%20raja%20podat%27%20ruroy.mp3"},{"comment":"Кунц Дин - До рая подать рукой download","file":"https://archive.org/download/059DoRajaPodatRuroy/013_Do%20raja%20podat%27%20ruroy.mp3"},{"comment":"Кунц Дин - До рая подать рукой download","file":"https://archive.org/download/059DoRajaPodatRuroy/014_Do%20raja%20podat%27%20ruroy.mp3"},{"comment":"Кунц Дин - До рая подать рукой download","file":"https://archive.org/download/059DoRajaPodatRuroy/015_Do%20raja%20podat%27%20ruroy.mp3"},{"comment":"Кунц Дин - До рая подать рукой download","file":"https://archive.org/download/059DoRajaPodatRuroy/016_Do%20raja%20podat%27%20ruroy.mp3"},{"comment":"Кунц Дин - До рая подать рукой download","file":"https://archive.org/download/059DoRajaPodatRuroy/017_Do%20raja%20podat%27%20ruroy.mp3"},{"comment":"Кунц Дин - До рая подать рукой download","file":"https://archive.org/download/059DoRajaPodatRuroy/018_Do%20raja%20podat%27%20ruroy.mp3"},{"comment":"Кунц Дин - До рая подать рукой download","file":"https://archive.org/download/059DoRajaPodatRuroy/019_Do%20raja%20podat%27%20ruroy.mp3"},{"comment":"Кунц Дин - До рая подать рукой download","file":"https://archive.org/download/059DoRajaPodatRuroy/020_Do%20raja%20podat%27%20ruroy.mp3"},{"comment":"Кунц Дин - До рая подать рукой download","file":"https://archive.org/download/059DoRajaPodatRuroy/021_Do%20raja%20podat%27%20ruroy.mp3"},{"comment":"Кунц Дин - До рая подать рукой download","file":"https://archive.org/download/059DoRajaPodatRuroy/022_Do%20raja%20podat%27%20ruroy.mp3"},{"comment":"Кунц Дин - До рая подать рукой download","file":"https://archive.org/download/059DoRajaPodatRuroy/023_Do%20raja%20podat%27%20ruroy.mp3"},{"comment":"Кунц Дин - До рая подать рукой download","file":"https://archive.org/download/059DoRajaPodatRuroy/024_Do%20raja%20podat%27%20ruroy.mp3"},{"comment":"Кунц Дин - До рая подать рукой download","file":"https://archive.org/download/059DoRajaPodatRuroy/025_Do%20raja%20podat%27%20ruroy.mp3"},{"comment":"Кунц Дин - До рая подать рукой download","file":"https://archive.org/download/059DoRajaPodatRuroy/026_Do%20raja%20podat%27%20ruroy.mp3"},{"comment":"Кунц Дин - До рая подать рукой download","file":"https://archive.org/download/059DoRajaPodatRuroy/027_Do%20raja%20podat%27%20ruroy.mp3"},{"comment":"Кунц Дин - До рая подать рукой download","file":"https://archive.org/download/059DoRajaPodatRuroy/028_Do%20raja%20podat%27%20ruroy.mp3"},{"comment":"Кунц Дин - До рая подать рукой download","file":"https://archive.org/download/059DoRajaPodatRuroy/029_Do%20raja%20podat%27%20ruroy.mp3"},{"comment":"Кунц Дин - До рая подать рукой download","file":"https://archive.org/download/059DoRajaPodatRuroy/030_Do%20raja%20podat%27%20ruroy.mp3"},{"comment":"Кунц Дин - До рая подать рукой download","file":"https://archive.org/download/059DoRajaPodatRuroy/031_Do%20raja%20podat%27%20ruroy.mp3"},{"comment":"Кунц Дин - До рая подать рукой download","file":"https://archive.org/download/059DoRajaPodatRuroy/032_Do%20raja%20podat%27%20ruroy.mp3"},{"comment":"Кунц Дин - До рая подать рукой download","file":"https://archive.org/download/059DoRajaPodatRuroy/033_Do%20raja%20podat%27%20ruroy.mp3"},{"comment":"Кунц Дин - До рая подать рукой download","file":"https://archive.org/download/059DoRajaPodatRuroy/034_Do%20raja%20podat%27%20ruroy.mp3"},{"comment":"Кунц Дин - До рая подать рукой download","file":"https://archive.org/download/059DoRajaPodatRuroy/035_Do%20raja%20podat%27%20ruroy.mp3"},{"comment":"036_Do raja podat\u0027 ruroy download","file":"https://archive.org/download/059DoRajaPodatRuroy/036_doRajaPodatRuroy.mp3"},{"comment":"037_Do raja podat\u0027 ruroy download","file":"https://archive.org/download/059DoRajaPodatRuroy/037_doRajaPodatRuroy.mp3"},{"comment":"038_Do raja podat\u0027 ruroy download","file":"https://archive.org/download/059DoRajaPodatRuroy/038_doRajaPodatRuroy.mp3"},{"comment":"039_Do raja podat\u0027 ruroy download","file":"https://archive.org/download/059DoRajaPodatRuroy/039_doRajaPodatRuroy.mp3"},{"comment":"040_Do raja podat\u0027 ruroy download","file":"https://archive.org/download/059DoRajaPodatRuroy/040_doRajaPodatRuroy.mp3"},{"comment":"041_Do raja podat\u0027 ruroy download","file":"https://archive.org/download/059DoRajaPodatRuroy/041_doRajaPodatRuroy.mp3"},{"comment":"042_Do raja podat\u0027 ruroy download","file":"https://archive.org/download/059DoRajaPodatRuroy/042_doRajaPodatRuroy.mp3"},{"comment":"043_Do raja podat\u0027 ruroy download","file":"https://archive.org/download/059DoRajaPodatRuroy/043_doRajaPodatRuroy.mp3"},{"comment":"044_Do raja podat\u0027 ruroy download","file":"https://archive.org/download/059DoRajaPodatRuroy/044_doRajaPodatRuroy.mp3"},{"comment":"045_Do raja podat\u0027 ruroy download","file":"https://archive.org/download/059DoRajaPodatRuroy/045_doRajaPodatRuroy.mp3"},{"comment":"046_Do raja podat\u0027 ruroy download","file":"https://archive.org/download/059DoRajaPodatRuroy/046_doRajaPodatRuroy.mp3"},{"comment":"047_Do raja podat\u0027 ruroy download","file":"https://archive.org/download/059DoRajaPodatRuroy/047_doRajaPodatRuroy.mp3"},{"comment":"048_Do raja podat\u0027 ruroy download","file":"https://archive.org/download/059DoRajaPodatRuroy/048_doRajaPodatRuroy.mp3"},{"comment":"049_Do raja podat\u0027 ruroy download","file":"https://archive.org/download/059DoRajaPodatRuroy/049_doRajaPodatRuroy.mp3"},{"comment":"050_Do raja podat\u0027 ruroy download","file":"https://archive.org/download/059DoRajaPodatRuroy/050_doRajaPodatRuroy.mp3"},{"comment":"051_Do raja podat\u0027 ruroy download","file":"https://archive.org/download/059DoRajaPodatRuroy/051_doRajaPodatRuroy.mp3"},{"comment":"052_Do raja podat\u0027 ruroy download","file":"https://archive.org/download/059DoRajaPodatRuroy/052_doRajaPodatRuroy.mp3"},{"comment":"053_Do raja podat\u0027 ruroy download","file":"https://archive.org/download/059DoRajaPodatRuroy/053_doRajaPodatRuroy.mp3"},{"comment":"054_Do raja podat\u0027 ruroy download","file":"https://archive.org/download/059DoRajaPodatRuroy/054_doRajaPodatRuroy.mp3"},{"comment":"055_Do raja podat\u0027 ruroy download","file":"https://archive.org/download/059DoRajaPodatRuroy/055_doRajaPodatRuroy.mp3"},{"comment":"056_Do raja podat\u0027 ruroy download","file":"https://archive.org/download/059DoRajaPodatRuroy/056_doRajaPodatRuroy.mp3"},{"comment":"057_Do raja podat\u0027 ruroy download","file":"https://archive.org/download/059DoRajaPodatRuroy/057_doRajaPodatRuroy.mp3"},{"comment":"058_Do raja podat\u0027 ruroy download","file":"https://archive.org/download/059DoRajaPodatRuroy/058_doRajaPodatRuroy.mp3"},{"comment":"059_Do raja podat\u0027 ruroy download","file":"https://archive.org/download/059DoRajaPodatRuroy/059_doRajaPodatRuroy.mp3"},{"comment":"060_Do raja podat\u0027 ruroy download","file":"https://archive.org/download/059DoRajaPodatRuroy/060_doRajaPodatRuroy.mp3"},{"comment":"061_Do raja podat\u0027 ruroy download","file":"https://archive.org/download/059DoRajaPodatRuroy/061_doRajaPodatRuroy.mp3"},{"comment":"062_Do raja podat\u0027 ruroy download","file":"https://archive.org/download/059DoRajaPodatRuroy/062_doRajaPodatRuroy.mp3"},{"comment":"063_Do raja podat\u0027 ruroy download","file":"https://archive.org/download/059DoRajaPodatRuroy/063_doRajaPodatRuroy.mp3"},{"comment":"064_Do raja podat\u0027 ruroy download","file":"https://archive.org/download/059DoRajaPodatRuroy/064_doRajaPodatRuroy.mp3"},{"comment":"065_Do raja podat\u0027 ruroy download","file":"https://archive.org/download/059DoRajaPodatRuroy/065_doRajaPodatRuroy.mp3"},{"comment":"066_Do raja podat\u0027 ruroy download","file":"https://archive.org/download/059DoRajaPodatRuroy/066_doRajaPodatRuroy.mp3"},{"comment":"067_Do raja podat\u0027 ruroy download","file":"https://archive.org/download/059DoRajaPodatRuroy/067_doRajaPodatRuroy.mp3"},{"comment":"068_Do raja podat\u0027 ruroy download","file":"https://archive.org/download/059DoRajaPodatRuroy/068_doRajaPodatRuroy.mp3"},{"comment":"069_Do raja podat\u0027 ruroy download","file":"https://archive.org/download/059DoRajaPodatRuroy/069_doRajaPodatRuroy.mp3"},{"comment":"070_Do raja podat\u0027 ruroy download","file":"https://archive.org/download/059DoRajaPodatRuroy/070_doRajaPodatRuroy.mp3"},{"comment":"071_Do raja podat\u0027 ruroy download","file":"https://archive.org/download/059DoRajaPodatRuroy/071_doRajaPodatRuroy.mp3"},{"comment":"072_Do raja podat\u0027 ruroy download","file":"https://archive.org/download/059DoRajaPodatRuroy/072_doRajaPodatRuroy.mp3"},{"comment":"073_Do raja podat\u0027 ruroy download","file":"https://archive.org/download/059DoRajaPodatRuroy/073_doRajaPodatRuroy.mp3"},{"comment":"074_Do raja podat\u0027 ruroy download","file":"https://archive.org/download/059DoRajaPodatRuroy/074_doRajaPodatRuroy.mp3"},{"comment":"075_Do raja podat\u0027 ruroy download","file":"https://archive.org/download/059DoRajaPodatRuroy/075_doRajaPodatRuroy.mp3"},{"comment":"076_Do raja podat\u0027 ruroy download","file":"https://archive.org/download/059DoRajaPodatRuroy/076_doRajaPodatRuroy.mp3"},{"comment":"077_Do raja podat\u0027 ruroy download","file":"https://archive.org/download/059DoRajaPodatRuroy/077_doRajaPodatRuroy.mp3"},{"comment":"078_Do raja podat\u0027 ruroy download","file":"https://archive.org/download/059DoRajaPodatRuroy/078_doRajaPodatRuroy.mp3"},{"comment":"079_Do raja podat\u0027 ruroy download","file":"https://archive.org/download/059DoRajaPodatRuroy/079_doRajaPodatRuroy.mp3"},{"comment":"080_Do raja podat\u0027 ruroy download","file":"https://archive.org/download/059DoRajaPodatRuroy/080_doRajaPodatRuroy.mp3"},{"comment":"081_Do raja podat\u0027 ruroy download","file":"https://archive.org/download/059DoRajaPodatRuroy/081_doRajaPodatRuroy.mp3"},{"comment":"082_Do raja podat\u0027 ruroy download","file":"https://archive.org/download/059DoRajaPodatRuroy/082_doRajaPodatRuroy.mp3"},{"comment":"083_Do raja podat\u0027 ruroy download","file":"https://archive.org/download/059DoRajaPodatRuroy/083_doRajaPodatRuroy.mp3"},{"comment":"084_Do raja podat\u0027 ruroy download","file":"https://archive.org/download/059DoRajaPodatRuroy/084_doRajaPodatRuroy.mp3"},{"comment":"085_Do raja podat\u0027 ruroy download","file":"https://archive.org/download/059DoRajaPodatRuroy/085_doRajaPodatRuroy.mp3"},{"comment":"086_Do raja podat\u0027 ruroy download","file":"https://archive.org/download/059DoRajaPodatRuroy/086_doRajaPodatRuroy.mp3"},{"comment":"087_Do raja podat\u0027 ruroy download","file":"https://archive.org/download/059DoRajaPodatRuroy/087_doRajaPodatRuroy.mp3"},{"comment":"088_Do raja podat\u0027 ruroy download","file":"https://archive.org/download/059DoRajaPodatRuroy/088_doRajaPodatRuroy.mp3"},{"comment":"089_Do raja podat\u0027 ruroy download","file":"https://archive.org/download/059DoRajaPodatRuroy/089_doRajaPodatRuroy.mp3"},{"comment":"090_Do raja podat\u0027 ruroy download","file":"https://archive.org/download/059DoRajaPodatRuroy/090_doRajaPodatRuroy.mp3"},{"comment":"091_Do raja podat\u0027 ruroy download","file":"https://archive.org/download/059DoRajaPodatRuroy/091_doRajaPodatRuroy.mp3"},{"comment":"092_Do raja podat\u0027 ruroy download","file":"https://archive.org/download/059DoRajaPodatRuroy/092_doRajaPodatRuroy.mp3"},{"comment":"093_Do raja podat\u0027 ruroy download","file":"https://archive.org/download/059DoRajaPodatRuroy/093_doRajaPodatRuroy.mp3"},{"comment":"094_Do raja podat\u0027 ruroy download","file":"https://archive.org/download/059DoRajaPodatRuroy/094_doRajaPodatRuroy.mp3"},{"comment":"095_Do raja podat\u0027 ruroy download","file":"https://archive.org/download/059DoRajaPodatRuroy/095_doRajaPodatRuroy.mp3"},{"comment":"096_Do raja podat\u0027 ruroy download","file":"https://archive.org/download/059DoRajaPodatRuroy/096_doRajaPodatRuroy.mp3"},{"comment":"097_Do raja podat\u0027 ruroy download","file":"https://archive.org/download/059DoRajaPodatRuroy/097_doRajaPodatRuroy.mp3"},{"comment":"098_Do raja podat\u0027 ruroy download","file":"https://archive.org/download/059DoRajaPodatRuroy/098_doRajaPodatRuroy.mp3"},{"comment":"099_Do raja podat\u0027 ruroy download","file":"https://archive.org/download/059DoRajaPodatRuroy/099_doRajaPodatRuroy.mp3"},{"comment":"100_Do raja podat\u0027 ruroy download","file":"https://archive.org/download/059DoRajaPodatRuroy/100_doRajaPodatRuroy.mp3"},{"comment":"101_Do raja podat\u0027 ruroy download","file":"https://archive.org/download/059DoRajaPodatRuroy/101_doRajaPodatRuroy.mp3"},{"comment":"102_Do raja podat\u0027 ruroy download","file":"https://archive.org/download/059DoRajaPodatRuroy/102_doRajaPodatRuroy.mp3"},{"comment":"103_Do raja podat\u0027 ruroy download","file":"https://archive.org/download/059DoRajaPodatRuroy/103_doRajaPodatRuroy.mp3"},{"comment":"104_Do raja podat\u0027 ruroy download","file":"https://archive.org/download/059DoRajaPodatRuroy/104_doRajaPodatRuroy.mp3"},{"comment":"105_Do raja podat\u0027 ruroy download","file":"https://archive.org/download/059DoRajaPodatRuroy/105_doRajaPodatRuroy.mp3"}]}
